pdf2slides/__init__.py
pdf2slides/converter.py
pdf2slides-0.1.0.dist-info/LICENSE
pdf2slides-0.1.0.dist-info/METADATA
pdf2slides-0.1.0.dist-info/WHEEL
pdf2slides-0.1.0.dist-info/top_level.txt
pdf2slides-0.1.0.dist-info/RECORD
