Metadata-Version: 2.1
Name: pdf2slides
Version: 0.1.0
Summary: Convert a PDF file into editable slides in .pptx format
Home-page: https://github.com/ha0ranyu/pdf2slides
Author: Haoran Yu
Classifier: Development Status :: 4 - Beta
Classifier: Intended Audience :: Developers
Classifier: License :: OSI Approved :: GNU General Public License v3 (GPLv3)
Classifier: Programming Language :: Python :: 3
Classifier: Programming Language :: Python :: 3.9
Classifier: Programming Language :: Python :: 3.10
Classifier: Programming Language :: Python :: 3.11
Classifier: Programming Language :: Python :: 3.12
License-File: LICENSE
Requires-Dist: numpy
Requires-Dist: paddleocr
Requires-Dist: paddlepaddle
Requires-Dist: pillow
Requires-Dist: PyMuPDF
Requires-Dist: python-pptx
Requires-Dist: scikit-learn
